{"Aurora, IL":{"name":"Aurora","state":"IL","composite":61,"factors":{"zoning":18,"process":9,"site":13,"competition":10,"political":12},"carwash":{"status":"conditional","score":62,"pathway":"Permitted","zones":"B-2, B-3, M-1","special_use":false},"drivethru":{"status":"conditional","score":62,"pathway":"Permitted","zones":"B-2, B-3, B-4","special_use":false,"stacking_cars":6},"collision":{"status":"conditional","score":58,"pathway":"Conditional Use","zones":"M-1, M-2","special_use":true},"autosales":{"status":"conditional","score":60,"pathway":"Permitted","zones":"B-3, B-4, M-1","special_use":false},"requirements":{"stacking_cars":6,"lot_size_sqft":null,"front_setback_ft":null},"stacking_issue":false,"moratorium":false,"zoning_map_url":"https://gis.aurora-il.org","confidence":"AI Estimate","verified":false,"override_reason":"","notes":"Pro-development, but large city = process friction.","population":197000},"Joliet, IL":{"name":"Joliet","state":"IL","composite":64,"factors":{"zoning":18,"process":10,"site":13,"competition":11,"political":12},"carwash":{"status":"conditional","score":64,"pathway":"Permitted","zones":"B-3, B-4","special_use":false},"drivethru":{"status":"conditional","score":64,"pathway":"Permitted","zones":"B-3, B-4, B-5","special_use":false,"stacking_cars":6},"collision":{"status":"conditional","score":62,"pathway":"Permitted","zones":"B-4, M-1, M-2","special_use":false},"autosales":{"status":"conditional","score":64,"pathway":"Permitted","zones":"B-3, B-4, B-5","special_use":false},"requirements":{"stacking_cars":6,"lot_size_sqft":null,"front_setback_ft":null},"stacking_issue":false,"moratorium":false,"zoning_map_url":"https://www.joliet.gov/departments/community-development/gis-maps","confidence":"AI Estimate","verified":false,"override_reason":"","notes":"Business-friendly but growing = competition.","population":148000},"Des Plaines, IL":{"name":"Des Plaines","state":"IL","composite":60,"factors":{"zoning":18,"process":9,"site":13,"competition":11,"political":11},"carwash":{"status":"conditional","score":62,"pathway":"Permitted","zones":"C-3, C-4","special_use":false},"drivethru":{"status":"conditional","score":60,"pathway":"Permitted","zones":"C-3, C-4","special_use":false,"stacking_cars":8},"collision":{"status":"conditional","score":56,"pathway":"Conditional Use","zones":"C-4, M-1","special_use":true},"autosales":{"status":"conditional","score":60,"pathway":"Permitted","zones":"C-3, C-4","special_use":false},"requirements":{"stacking_cars":8,"lot_size_sqft":null,"front_setback_ft":null},"stacking_issue":false,"moratorium":false,"zoning_map_url":"https://www.desplaines.org/maps","confidence":"AI Estimate","verified":false,"override_reason":"","notes":"8-car stacking per Sec. 12-9-4.","population":58000},"Bolingbrook, IL":{"name":"Bolingbrook","state":"IL","composite":66,"factors":{"zoning":18,"process":11,"site":14,"competition":12,"political":12},"carwash":{"status":"likely_permitted","score":67,"pathway":"Permitted","zones":"C-2, C-3","special_use":false},"drivethru":{"status":"likely_permitted","score":67,"pathway":"Permitted","zones":"C-2, C-3","special_use":false,"stacking_cars":6},"collision":{"status":"likely_permitted","score":65,"pathway":"Permitted","zones":"C-3, M-1","special_use":false},"autosales":{"status":"likely_permitted","score":65,"pathway":"Permitted","zones":"C-2, C-3","special_use":false},"requirements":{"stacking_cars":6,"lot_size_sqft":null,"front_setback_ft":null},"stacking_issue":false,"moratorium":false,"zoning_map_url":"","confidence":"AI Estimate","verified":false,"override_reason":"","notes":"Growth-oriented but IL process friction.","population":73000},"Plainfield, IL":{"name":"Plainfield","state":"IL","composite":74,"factors":{"zoning":18,"process":13,"site":16,"competition":14,"political":14},"carwash":{"status":"likely_permitted","score":75,"pathway":"Permitted","zones":"B-3, B-4","special_use":false},"drivethru":{"status":"likely_permitted","score":75,"pathway":"Permitted","zones":"B-3, B-4","special_use":false,"stacking_cars":6},"collision":{"status":"likely_permitted","score":73,"pathway":"Permitted","zones":"B-4, M-1","special_use":false},"autosales":{"status":"likely_permitted","score":73,"pathway":"Permitted","zones":"B-3, B-4","special_use":false},"requirements":{"stacking_cars":6,"lot_size_sqft":null,"front_setback_ft":null},"stacking_issue":false,"moratorium":false,"zoning_map_url":"","confidence":"AI Estimate","verified":false,"override_reason":"","notes":"Rapidly growing. Less competition. Pro-development.","population":41000},"Romeoville, IL":{"name":"Romeoville","state":"IL","composite":74,"factors":{"zoning":18,"process":13,"site":15,"competition":14,"political":14},"carwash":{"status":"likely_permitted","score":74,"pathway":"Permitted","zones":"C-2, C-3","special_use":false},"drivethru":{"status":"likely_permitted","score":74,"pathway":"Permitted","zones":"C-2, C-3","special_use":false,"stacking_cars":5},"collision":{"status":"likely_permitted","score":72,"pathway":"Permitted","zones":"C-3, M-1","special_use":false},"autosales":{"status":"likely_permitted","score":74,"pathway":"Permitted","zones":"C-2, C-3","special_use":false},"requirements":{"stacking_cars":5,"lot_size_sqft":null,"front_setback_ft":null},"stacking_issue":false,"moratorium":false,"zoning_map_url":"","confidence":"AI Estimate","verified":false,"override_reason":"","notes":"","population":39000},"Addison, IL":{"name":"Addison","state":"IL","composite":69,"factors":{"zoning":18,"process":12,"site":14,"competition":13,"political":13},"carwash":{"status":"likely_permitted","score":70,"pathway":"Permitted","zones":"B-3, M-1","special_use":false},"drivethru":{"status":"likely_permitted","score":70,"pathway":"Permitted","zones":"B-3","special_use":false,"stacking_cars":6},"collision":{"status":"likely_permitted","score":68,"pathway":"Permitted","zones":"M-1, M-2","special_use":false},"autosales":{"status":"likely_permitted","score":68,"pathway":"Permitted","zones":"B-3, M-1","special_use":false},"requirements":{"stacking_cars":6,"lot_size_sqft":null,"front_setback_ft":null},"stacking_issue":false,"moratorium":false,"zoning_map_url":"","confidence":"AI Estimate","verified":false,"override_reason":"","notes":"","population":36000},"Carol Stream, IL":{"name":"Carol Stream","state":"IL","composite":69,"factors":{"zoning":18,"process":12,"site":14,"competition":13,"political":13},"carwash":{"status":"likely_permitted","score":70,"pathway":"Permitted","zones":"B-2, B-3","special_use":false},"drivethru":{"status":"likely_permitted","score":70,"pathway":"Permitted","zones":"B-2, B-3","special_use":false,"stacking_cars":6},"collision":{"status":"likely_permitted","score":68,"pathway":"Permitted","zones":"B-3, M-1","special_use":false},"autosales":{"status":"likely_permitted","score":68,"pathway":"Permitted","zones":"B-2, B-3","special_use":false},"requirements":{"stacking_cars":6,"lot_size_sqft":null,"front_setback_ft":null},"stacking_issue":false,"moratorium":false,"zoning_map_url":"","confidence":"AI Estimate","verified":false,"override_reason":"","notes":"","population":40000},"Glendale Heights, IL":{"name":"Glendale Heights","state":"IL","composite":69,"factors":{"zoning":18,"process":12,"site":14,"competition":13,"political":13},"carwash":{"status":"likely_permitted","score":70,"pathway":"Permitted","zones":"B-2, B-3","special_use":false},"drivethru":{"status":"likely_permitted","score":70,"pathway":"Permitted","zones":"B-2, B-3","special_use":false,"stacking_cars":6},"collision":{"status":"likely_permitted","score":68,"pathway":"Permitted","zones":"B-3, M-1","special_use":false},"autosales":{"status":"likely_permitted","score":68,"pathway":"Permitted","zones":"B-2, B-3","special_use":false},"requirements":{"stacking_cars":6,"lot_size_sqft":null,"front_setback_ft":null},"stacking_issue":false,"moratorium":false,"zoning_map_url":"","confidence":"AI Estimate","verified":false,"override_reason":"","notes":"","population":34000},"Bloomingdale, IL":{"name":"Bloomingdale","state":"IL","composite":75,"factors":{"zoning":18,"process":13,"site":16,"competition":15,"political":14},"carwash":{"status":"likely_permitted","score":76,"pathway":"Permitted","zones":"B-2, B-3","special_use":false},"drivethru":{"status":"likely_permitted","score":76,"pathway":"Permitted","zones":"B-2, B-3","special_use":false,"stacking_cars":6},"collision":{"status":"likely_permitted","score":74,"pathway":"Permitted","zones":"B-3, M-1","special_use":false},"autosales":{"status":"likely_permitted","score":74,"pathway":"Permitted","zones":"B-2, B-3","special_use":false},"requirements":{"stacking_cars":6,"lot_size_sqft":null,"front_setback_ft":null},"stacking_issue":false,"moratorium":false,"zoning_map_url":"","confidence":"AI Estimate","verified":false,"override_reason":"","notes":"","population":22000},"Bensenville, IL":{"name":"Bensenville","state":"IL","composite":79,"factors":{"zoning":18,"process":14,"site":16,"competition":16,"political":15},"carwash":{"status":"likely_permitted","score":79,"pathway":"Permitted","zones":"B-2, B-3","special_use":false},"drivethru":{"status":"likely_permitted","score":79,"pathway":"Permitted","zones":"B-2, B-3","special_use":false,"stacking_cars":5},"collision":{"status":"likely_permitted","score":77,"pathway":"Permitted","zones":"B-3, M-1","special_use":false},"autosales":{"status":"likely_permitted","score":79,"pathway":"Permitted","zones":"B-2, B-3","special_use":false},"requirements":{"stacking_cars":5,"lot_size_sqft":null,"front_setback_ft":null},"stacking_issue":false,"moratorium":false,"zoning_map_url":"","confidence":"AI Estimate","verified":false,"override_reason":"","notes":"","population":21000},"Wood Dale, IL":{"name":"Wood Dale","state":"IL","composite":79,"factors":{"zoning":18,"process":14,"site":16,"competition":16,"political":15},"carwash":{"status":"likely_permitted","score":79,"pathway":"Permitted","zones":"B-2, B-3","special_use":false},"drivethru":{"status":"likely_permitted","score":79,"pathway":"Permitted","zones":"B-2, B-3","special_use":false,"stacking_cars":5},"collision":{"status":"likely_permitted","score":77,"pathway":"Permitted","zones":"B-3, M-1","special_use":false},"autosales":{"status":"likely_permitted","score":79,"pathway":"Permitted","zones":"B-2, B-3","special_use":false},"requirements":{"stacking_cars":5,"lot_size_sqft":null,"front_setback_ft":null},"stacking_issue":false,"moratorium":false,"zoning_map_url":"","confidence":"AI Estimate","verified":false,"override_reason":"","notes":"","population":14000},"Itasca, IL":{"name":"Itasca","state":"IL","composite":83,"factors":{"zoning":18,"process":15,"site":16,"competition":18,"political":16},"carwash":{"status":"permitted","score":83,"pathway":"Permitted","zones":"B-2","special_use":false},"drivethru":{"status":"permitted","score":83,"pathway":"Permitted","zones":"B-2","special_use":false,"stacking_cars":5},"collision":{"status":"permitted","score":81,"pathway":"Permitted","zones":"B-2, M-1","special_use":false},"autosales":{"status":"permitted","score":83,"pathway":"Permitted","zones":"B-2","special_use":false},"requirements":{"stacking_cars":5,"lot_size_sqft":null,"front_setback_ft":null},"stacking_issue":false,"moratorium":false,"zoning_map_url":"","confidence":"AI Estimate","verified":false,"override_reason":"","notes":"Small town \u2014 less competition but limited sites.","population":8500},"Elk Grove Village, IL":{"name":"Elk Grove Village","state":"IL","composite":70,"factors":{"zoning":18,"process":12,"site":15,"competition":13,"political":13},"carwash":{"status":"likely_permitted","score":71,"pathway":"Permitted","zones":"B-2, B-3","special_use":false},"drivethru":{"status":"likely_permitted","score":71,"pathway":"Permitted","zones":"B-2, B-3","special_use":false,"stacking_cars":6},"collision":{"status":"likely_permitted","score":69,"pathway":"Permitted","zones":"B-3, M-1","special_use":false},"autosales":{"status":"likely_permitted","score":69,"pathway":"Permitted","zones":"B-2, B-3","special_use":false},"requirements":{"stacking_cars":6,"lot_size_sqft":null,"front_setback_ft":null},"stacking_issue":false,"moratorium":false,"zoning_map_url":"https://www.elkgrove.org/gis","confidence":"AI Estimate","verified":false,"override_reason":"","notes":"","population":32000},"Waukegan, IL":{"name":"Waukegan","state":"IL","composite":65,"factors":{"zoning":18,"process":11,"site":14,"competition":12,"political":11},"carwash":{"status":"likely_permitted","score":66,"pathway":"Permitted","zones":"B-3, B-4","special_use":false},"drivethru":{"status":"likely_permitted","score":66,"pathway":"Permitted","zones":"B-3, B-4","special_use":false,"stacking_cars":6},"collision":{"status":"conditional","score":64,"pathway":"Permitted","zones":"B-4, M-1","special_use":false},"autosales":{"status":"conditional","score":64,"pathway":"Permitted","zones":"B-3, B-4","special_use":false},"requirements":{"stacking_cars":6,"lot_size_sqft":null,"front_setback_ft":null},"stacking_issue":false,"moratorium":false,"zoning_map_url":"","confidence":"AI Estimate","verified":false,"override_reason":"","notes":"","population":87000},"Antioch, IL":{"name":"Antioch","state":"IL","composite":80,"factors":{"zoning":18,"process":14,"site":16,"competition":17,"political":15},"carwash":{"status":"permitted","score":80,"pathway":"Permitted","zones":"B-2, B-3","special_use":false},"drivethru":{"status":"permitted","score":80,"pathway":"Permitted","zones":"B-2, B-3","special_use":false,"stacking_cars":5},"collision":{"status":"likely_permitted","score":78,"pathway":"Permitted","zones":"B-3, M-1","special_use":false},"autosales":{"status":"permitted","score":80,"pathway":"Permitted","zones":"B-2, B-3","special_use":false},"requirements":{"stacking_cars":5,"lot_size_sqft":null,"front_setback_ft":null},"stacking_issue":false,"moratorium":false,"zoning_map_url":"","confidence":"AI Estimate","verified":false,"override_reason":"","notes":"","population":14000},"Round Lake, IL":{"name":"Round Lake","state":"IL","composite":80,"factors":{"zoning":18,"process":14,"site":16,"competition":17,"political":15},"carwash":{"status":"permitted","score":80,"pathway":"Permitted","zones":"C-2, C-3","special_use":false},"drivethru":{"status":"permitted","score":80,"pathway":"Permitted","zones":"C-2, C-3","special_use":false,"stacking_cars":5},"collision":{"status":"likely_permitted","score":78,"pathway":"Permitted","zones":"C-3, M-1","special_use":false},"autosales":{"status":"permitted","score":80,"pathway":"Permitted","zones":"C-2, C-3","special_use":false},"requirements":{"stacking_cars":5,"lot_size_sqft":null,"front_setback_ft":null},"stacking_issue":false,"moratorium":false,"zoning_map_url":"","confidence":"AI Estimate","verified":false,"override_reason":"","notes":"","population":18500},"Mundelein, IL":{"name":"Mundelein","state":"IL","composite":69,"factors":{"zoning":18,"process":12,"site":14,"competition":13,"political":13},"carwash":{"status":"likely_permitted","score":70,"pathway":"Permitted","zones":"B-3, B-4","special_use":false},"drivethru":{"status":"likely_permitted","score":70,"pathway":"Permitted","zones":"B-3, B-4","special_use":false,"stacking_cars":6},"collision":{"status":"likely_permitted","score":68,"pathway":"Permitted","zones":"B-4, M-1","special_use":false},"autosales":{"status":"likely_permitted","score":68,"pathway":"Permitted","zones":"B-3, B-4","special_use":false},"requirements":{"stacking_cars":6,"lot_size_sqft":null,"front_setback_ft":null},"stacking_issue":false,"moratorium":false,"zoning_map_url":"","confidence":"AI Estimate","verified":false,"override_reason":"","notes":"","population":31000},"Grayslake, IL":{"name":"Grayslake","state":"IL","composite":79,"factors":{"zoning":18,"process":14,"site":16,"competition":16,"political":15},"carwash":{"status":"likely_permitted","score":79,"pathway":"Permitted","zones":"B-2, B-3","special_use":false},"drivethru":{"status":"likely_permitted","score":79,"pathway":"Permitted","zones":"B-2, B-3","special_use":false,"stacking_cars":5},"collision":{"status":"likely_permitted","score":77,"pathway":"Permitted","zones":"B-3, M-1","special_use":false},"autosales":{"status":"likely_permitted","score":79,"pathway":"Permitted","zones":"B-2, B-3","special_use":false},"requirements":{"stacking_cars":5,"lot_size_sqft":null,"front_setback_ft":null},"stacking_issue":false,"moratorium":false,"zoning_map_url":"","confidence":"AI Estimate","verified":false,"override_reason":"","notes":"","population":21000},"Tinley Park, IL":{"name":"Tinley Park","state":"IL","composite":62,"factors":{"zoning":18,"process":10,"site":13,"competition":11,"political":11},"carwash":{"status":"conditional","score":63,"pathway":"Permitted","zones":"B-3, B-4","special_use":false},"drivethru":{"status":"conditional","score":63,"pathway":"Permitted","zones":"B-3, B-4","special_use":false,"stacking_cars":6},"collision":{"status":"conditional","score":61,"pathway":"Permitted","zones":"B-4, M-1","special_use":false},"autosales":{"status":"conditional","score":61,"pathway":"Permitted","zones":"B-3, B-4","special_use":false},"requirements":{"stacking_cars":6,"lot_size_sqft":null,"front_setback_ft":null},"stacking_issue":false,"moratorium":false,"zoning_map_url":"","confidence":"AI Estimate","verified":false,"override_reason":"","notes":"","population":57000},"Homer Glen, IL":{"name":"Homer Glen","state":"IL","composite":76,"factors":{"zoning":18,"process":13,"site":16,"competition":16,"political":14},"carwash":{"status":"likely_permitted","score":77,"pathway":"Permitted","zones":"B-2, B-3","special_use":false},"drivethru":{"status":"likely_permitted","score":77,"pathway":"Permitted","zones":"B-2, B-3","special_use":false,"stacking_cars":6},"collision":{"status":"likely_permitted","score":75,"pathway":"Permitted","zones":"B-3, M-1","special_use":false},"autosales":{"status":"likely_permitted","score":75,"pathway":"Permitted","zones":"B-2, B-3","special_use":false},"requirements":{"stacking_cars":6,"lot_size_sqft":null,"front_setback_ft":null},"stacking_issue":false,"moratorium":false,"zoning_map_url":"","confidence":"AI Estimate","verified":false,"override_reason":"","notes":"","population":21500},"Blue Island, IL":{"name":"Blue Island","state":"IL","composite":74,"factors":{"zoning":18,"process":13,"site":16,"competition":15,"political":13},"carwash":{"status":"likely_permitted","score":75,"pathway":"Permitted","zones":"C-2, C-3","special_use":false},"drivethru":{"status":"likely_permitted","score":75,"pathway":"Permitted","zones":"C-2, C-3","special_use":false,"stacking_cars":6},"collision":{"status":"likely_permitted","score":73,"pathway":"Permitted","zones":"C-3, M-1","special_use":false},"autosales":{"status":"likely_permitted","score":73,"pathway":"Permitted","zones":"C-2, C-3","special_use":false},"requirements":{"stacking_cars":6,"lot_size_sqft":null,"front_setback_ft":null},"stacking_issue":false,"moratorium":false,"zoning_map_url":"","confidence":"AI Estimate","verified":false,"override_reason":"","notes":"","population":23000},"Alsip, IL":{"name":"Alsip","state":"IL","composite":76,"factors":{"zoning":18,"process":13,"site":16,"competition":15,"political":14},"carwash":{"status":"likely_permitted","score":76,"pathway":"Permitted","zones":"C-2, C-3","special_use":false},"drivethru":{"status":"likely_permitted","score":76,"pathway":"Permitted","zones":"C-2, C-3","special_use":false,"stacking_cars":5},"collision":{"status":"likely_permitted","score":74,"pathway":"Permitted","zones":"C-3, M-1","special_use":false},"autosales":{"status":"likely_permitted","score":76,"pathway":"Permitted","zones":"C-2, C-3","special_use":false},"requirements":{"stacking_cars":5,"lot_size_sqft":null,"front_setback_ft":null},"stacking_issue":false,"moratorium":false,"zoning_map_url":"","confidence":"AI Estimate","verified":false,"override_reason":"","notes":"","population":19000},"Oak Forest, IL":{"name":"Oak Forest","state":"IL","composite":70,"factors":{"zoning":18,"process":12,"site":14,"competition":14,"political":13},"carwash":{"status":"likely_permitted","score":71,"pathway":"Permitted","zones":"B-2, B-3","special_use":false},"drivethru":{"status":"likely_permitted","score":71,"pathway":"Permitted","zones":"B-2, B-3","special_use":false,"stacking_cars":6},"collision":{"status":"likely_permitted","score":69,"pathway":"Permitted","zones":"B-3, M-1","special_use":false},"autosales":{"status":"likely_permitted","score":69,"pathway":"Permitted","zones":"B-2, B-3","special_use":false},"requirements":{"stacking_cars":6,"lot_size_sqft":null,"front_setback_ft":null},"stacking_issue":false,"moratorium":false,"zoning_map_url":"","confidence":"AI Estimate","verified":false,"override_reason":"","notes":"","population":28000},"Berwyn, IL":{"name":"Berwyn","state":"IL","composite":60,"factors":{"zoning":18,"process":10,"site":12,"competition":11,"political":11},"carwash":{"status":"conditional","score":62,"pathway":"Permitted","zones":"C-2, C-3","special_use":false},"drivethru":{"status":"conditional","score":62,"pathway":"Permitted","zones":"C-2, C-3","special_use":false,"stacking_cars":6},"collision":{"status":"conditional","score":56,"pathway":"Conditional Use","zones":"C-3, M-1","special_use":true},"autosales":{"status":"conditional","score":58,"pathway":"Permitted","zones":"C-2, C-3","special_use":false},"requirements":{"stacking_cars":6,"lot_size_sqft":null,"front_setback_ft":null},"stacking_issue":false,"moratorium":false,"zoning_map_url":"","confidence":"AI Estimate","verified":false,"override_reason":"","notes":"Dense inner suburb. Limited parcels.","population":55000},"Cicero, IL":{"name":"Cicero","state":"IL","composite":58,"factors":{"zoning":18,"process":9,"site":12,"competition":10,"political":10},"carwash":{"status":"conditional","score":59,"pathway":"Permitted","zones":"C-2, C-3","special_use":false},"drivethru":{"status":"conditional","score":59,"pathway":"Permitted","zones":"C-2, C-3","special_use":false,"stacking_cars":6},"collision":{"status":"conditional","score":55,"pathway":"Permitted","zones":"C-3, M-1","special_use":false},"autosales":{"status":"conditional","score":57,"pathway":"Permitted","zones":"C-2, C-3","special_use":false},"requirements":{"stacking_cars":6,"lot_size_sqft":null,"front_setback_ft":null},"stacking_issue":false,"moratorium":false,"zoning_map_url":"","confidence":"AI Estimate","verified":false,"override_reason":"","notes":"Dense. Political complexity.","population":84000},"Melrose Park, IL":{"name":"Melrose Park","state":"IL","composite":75,"factors":{"zoning":18,"process":13,"site":15,"competition":15,"political":14},"carwash":{"status":"likely_permitted","score":75,"pathway":"Permitted","zones":"C-2","special_use":false},"drivethru":{"status":"likely_permitted","score":75,"pathway":"Permitted","zones":"C-2","special_use":false,"stacking_cars":5},"collision":{"status":"likely_permitted","score":73,"pathway":"Permitted","zones":"C-2, M-1","special_use":false},"autosales":{"status":"likely_permitted","score":75,"pathway":"Permitted","zones":"C-2","special_use":false},"requirements":{"stacking_cars":5,"lot_size_sqft":null,"front_setback_ft":null},"stacking_issue":false,"moratorium":false,"zoning_map_url":"","confidence":"AI Estimate","verified":false,"override_reason":"","notes":"","population":23000},"Bellwood, IL":{"name":"Bellwood","state":"IL","composite":76,"factors":{"zoning":18,"process":13,"site":15,"competition":16,"political":14},"carwash":{"status":"likely_permitted","score":76,"pathway":"Permitted","zones":"C-2","special_use":false},"drivethru":{"status":"likely_permitted","score":76,"pathway":"Permitted","zones":"C-2","special_use":false,"stacking_cars":5},"collision":{"status":"likely_permitted","score":74,"pathway":"Permitted","zones":"C-2, M-1","special_use":false},"autosales":{"status":"likely_permitted","score":76,"pathway":"Permitted","zones":"C-2","special_use":false},"requirements":{"stacking_cars":5,"lot_size_sqft":null,"front_setback_ft":null},"stacking_issue":false,"moratorium":false,"zoning_map_url":"","confidence":"AI Estimate","verified":false,"override_reason":"","notes":"","population":19000},"Warrenville, IL":{"name":"Warrenville","state":"IL","composite":79,"factors":{"zoning":18,"process":14,"site":15,"competition":17,"political":15},"carwash":{"status":"likely_permitted","score":79,"pathway":"Permitted","zones":"B-2","special_use":false},"drivethru":{"status":"likely_permitted","score":79,"pathway":"Permitted","zones":"B-2","special_use":false,"stacking_cars":5},"collision":{"status":"likely_permitted","score":77,"pathway":"Permitted","zones":"B-2, M-1","special_use":false},"autosales":{"status":"likely_permitted","score":79,"pathway":"Permitted","zones":"B-2","special_use":false},"requirements":{"stacking_cars":5,"lot_size_sqft":null,"front_setback_ft":null},"stacking_issue":false,"moratorium":false,"zoning_map_url":"","confidence":"AI Estimate","verified":false,"override_reason":"","notes":"","population":13000},"Winfield, IL":{"name":"Winfield","state":"IL","composite":83,"factors":{"zoning":18,"process":15,"site":16,"competition":18,"political":16},"carwash":{"status":"permitted","score":83,"pathway":"Permitted","zones":"B-2","special_use":false},"drivethru":{"status":"permitted","score":83,"pathway":"Permitted","zones":"B-2","special_use":false,"stacking_cars":5},"collision":{"status":"permitted","score":81,"pathway":"Permitted","zones":"B-2, M-1","special_use":false},"autosales":{"status":"permitted","score":83,"pathway":"Permitted","zones":"B-2","special_use":false},"requirements":{"stacking_cars":5,"lot_size_sqft":null,"front_setback_ft":null},"stacking_issue":false,"moratorium":false,"zoning_map_url":"","confidence":"AI Estimate","verified":false,"override_reason":"","notes":"","population":9200},"Villa Park, IL":{"name":"Villa Park","state":"IL","composite":73,"factors":{"zoning":18,"process":13,"site":15,"competition":14,"political":14},"carwash":{"status":"likely_permitted","score":74,"pathway":"Permitted","zones":"B-2, B-3","special_use":false},"drivethru":{"status":"likely_permitted","score":74,"pathway":"Permitted","zones":"B-2, B-3","special_use":false,"stacking_cars":6},"collision":{"status":"likely_permitted","score":72,"pathway":"Permitted","zones":"B-3, M-1","special_use":false},"autosales":{"status":"likely_permitted","score":72,"pathway":"Permitted","zones":"B-2, B-3","special_use":false},"requirements":{"stacking_cars":6,"lot_size_sqft":null,"front_setback_ft":null},"stacking_issue":false,"moratorium":false,"zoning_map_url":"","confidence":"AI Estimate","verified":false,"override_reason":"","notes":"","population":22000},"Lockport, IL":{"name":"Lockport","state":"IL","composite":71,"factors":{"zoning":18,"process":12,"site":15,"competition":14,"political":13},"carwash":{"status":"likely_permitted","score":72,"pathway":"Permitted","zones":"B-3, B-4","special_use":false},"drivethru":{"status":"likely_permitted","score":72,"pathway":"Permitted","zones":"B-3, B-4","special_use":false,"stacking_cars":6},"collision":{"status":"likely_permitted","score":70,"pathway":"Permitted","zones":"B-4, M-1","special_use":false},"autosales":{"status":"likely_permitted","score":70,"pathway":"Permitted","zones":"B-3, B-4","special_use":false},"requirements":{"stacking_cars":6,"lot_size_sqft":null,"front_setback_ft":null},"stacking_issue":false,"moratorium":false,"zoning_map_url":"","confidence":"AI Estimate","verified":false,"override_reason":"","notes":"","population":25000},"Green Bay, WI":{"name":"Green Bay","state":"WI","composite":67,"factors":{"zoning":18,"process":12,"site":13,"competition":11,"political":13},"carwash":{"status":"likely_permitted","score":67,"pathway":"Permitted","zones":"C-1, C-2, C-3","special_use":false},"drivethru":{"status":"likely_permitted","score":67,"pathway":"Permitted","zones":"C-1, C-2, C-3","special_use":false,"stacking_cars":6},"collision":{"status":"likely_permitted","score":65,"pathway":"Permitted","zones":"C-3, IL","special_use":false},"autosales":{"status":"likely_permitted","score":67,"pathway":"Permitted","zones":"C-2, C-3, IL","special_use":false},"requirements":{"stacking_cars":6,"lot_size_sqft":null,"front_setback_ft":null},"stacking_issue":false,"moratorium":false,"zoning_map_url":"https://greenbaywi.gov/gis","confidence":"AI Estimate","verified":false,"override_reason":"","notes":"","population":104000},"Wauwatosa, WI":{"name":"Wauwatosa","state":"WI","composite":68,"factors":{"zoning":18,"process":13,"site":14,"competition":12,"political":13},"carwash":{"status":"likely_permitted","score":70,"pathway":"Permitted","zones":"C-2, C-3","special_use":false},"drivethru":{"status":"likely_permitted","score":70,"pathway":"Permitted","zones":"C-2, C-3","special_use":false,"stacking_cars":6},"collision":{"status":"conditional","score":64,"pathway":"Conditional Use","zones":"C-3, IL","special_use":true},"autosales":{"status":"conditional","score":64,"pathway":"Conditional Use","zones":"C-3","special_use":true},"requirements":{"stacking_cars":6,"lot_size_sqft":null,"front_setback_ft":null},"stacking_issue":false,"moratorium":false,"zoning_map_url":"https://www.wauwatosa.net/government/gis-maps","confidence":"AI Estimate","verified":false,"override_reason":"","notes":"Collision/auto sales more restricted.","population":48000},"Oak Creek, WI":{"name":"Oak Creek","state":"WI","composite":77,"factors":{"zoning":18,"process":15,"site":15,"competition":14,"political":15},"carwash":{"status":"likely_permitted","score":77,"pathway":"Permitted","zones":"B-3, B-4","special_use":false},"drivethru":{"status":"likely_permitted","score":77,"pathway":"Permitted","zones":"B-3, B-4","special_use":false,"stacking_cars":6},"collision":{"status":"likely_permitted","score":75,"pathway":"Permitted","zones":"B-4, M-1","special_use":false},"autosales":{"status":"likely_permitted","score":77,"pathway":"Permitted","zones":"B-3, B-4","special_use":false},"requirements":{"stacking_cars":6,"lot_size_sqft":null,"front_setback_ft":null},"stacking_issue":false,"moratorium":false,"zoning_map_url":"","confidence":"AI Estimate","verified":false,"override_reason":"","notes":"","population":36500},"Sun Prairie, WI":{"name":"Sun Prairie","state":"WI","composite":78,"factors":{"zoning":18,"process":15,"site":15,"competition":15,"political":15},"carwash":{"status":"likely_permitted","score":78,"pathway":"Permitted","zones":"CC, HC","special_use":false},"drivethru":{"status":"likely_permitted","score":78,"pathway":"Permitted","zones":"CC, HC","special_use":false,"stacking_cars":5},"collision":{"status":"likely_permitted","score":76,"pathway":"Permitted","zones":"HC, LI","special_use":false},"autosales":{"status":"likely_permitted","score":78,"pathway":"Permitted","zones":"CC, HC","special_use":false},"requirements":{"stacking_cars":5,"lot_size_sqft":null,"front_setback_ft":null},"stacking_issue":false,"moratorium":false,"zoning_map_url":"","confidence":"AI Estimate","verified":false,"override_reason":"","notes":"","population":32000},"Menomonee Falls, WI":{"name":"Menomonee Falls","state":"WI","composite":77,"factors":{"zoning":18,"process":15,"site":15,"competition":14,"political":15},"carwash":{"status":"likely_permitted","score":77,"pathway":"Permitted","zones":"B-3, B-4","special_use":false},"drivethru":{"status":"likely_permitted","score":77,"pathway":"Permitted","zones":"B-3, B-4","special_use":false,"stacking_cars":6},"collision":{"status":"likely_permitted","score":75,"pathway":"Permitted","zones":"B-4, M-1","special_use":false},"autosales":{"status":"likely_permitted","score":77,"pathway":"Permitted","zones":"B-3, B-4","special_use":false},"requirements":{"stacking_cars":6,"lot_size_sqft":null,"front_setback_ft":null},"stacking_issue":false,"moratorium":false,"zoning_map_url":"","confidence":"AI Estimate","verified":false,"override_reason":"","notes":"","population":35000},"Germantown, WI":{"name":"Germantown","state":"WI","composite":82,"factors":{"zoning":18,"process":16,"site":16,"competition":16,"political":16},"carwash":{"status":"permitted","score":82,"pathway":"Permitted","zones":"B-2, B-3","special_use":false},"drivethru":{"status":"permitted","score":82,"pathway":"Permitted","zones":"B-2, B-3","special_use":false,"stacking_cars":5},"collision":{"status":"permitted","score":80,"pathway":"Permitted","zones":"B-3, M-1","special_use":false},"autosales":{"status":"permitted","score":82,"pathway":"Permitted","zones":"B-2, B-3","special_use":false},"requirements":{"stacking_cars":5,"lot_size_sqft":null,"front_setback_ft":null},"stacking_issue":false,"moratorium":false,"zoning_map_url":"","confidence":"AI Estimate","verified":false,"override_reason":"","notes":"","population":20000},"West Bend, WI":{"name":"West Bend","state":"WI","composite":78,"factors":{"zoning":18,"process":15,"site":15,"competition":15,"political":15},"carwash":{"status":"likely_permitted","score":78,"pathway":"Permitted","zones":"B-3","special_use":false},"drivethru":{"status":"likely_permitted","score":78,"pathway":"Permitted","zones":"B-3","special_use":false,"stacking_cars":5},"collision":{"status":"likely_permitted","score":76,"pathway":"Permitted","zones":"B-3, M-1","special_use":false},"autosales":{"status":"likely_permitted","score":78,"pathway":"Permitted","zones":"B-3","special_use":false},"requirements":{"stacking_cars":5,"lot_size_sqft":null,"front_setback_ft":null},"stacking_issue":false,"moratorium":false,"zoning_map_url":"","confidence":"AI Estimate","verified":false,"override_reason":"","notes":"","population":32000},"De Pere, WI":{"name":"De Pere","state":"WI","composite":82,"factors":{"zoning":18,"process":16,"site":16,"competition":16,"political":16},"carwash":{"status":"permitted","score":82,"pathway":"Permitted","zones":"C-1, C-2","special_use":false},"drivethru":{"status":"permitted","score":82,"pathway":"Permitted","zones":"C-1, C-2","special_use":false,"stacking_cars":5},"collision":{"status":"permitted","score":80,"pathway":"Permitted","zones":"C-2, IL","special_use":false},"autosales":{"status":"permitted","score":82,"pathway":"Permitted","zones":"C-1, C-2","special_use":false},"requirements":{"stacking_cars":5,"lot_size_sqft":null,"front_setback_ft":null},"stacking_issue":false,"moratorium":false,"zoning_map_url":"","confidence":"AI Estimate","verified":false,"override_reason":"","notes":"","population":24000},"Ashwaubenon, WI":{"name":"Ashwaubenon","state":"WI","composite":82,"factors":{"zoning":18,"process":16,"site":16,"competition":16,"political":16},"carwash":{"status":"permitted","score":82,"pathway":"Permitted","zones":"C-1, C-2","special_use":false},"drivethru":{"status":"permitted","score":82,"pathway":"Permitted","zones":"C-1, C-2","special_use":false,"stacking_cars":5},"collision":{"status":"permitted","score":80,"pathway":"Permitted","zones":"C-2, IL","special_use":false},"autosales":{"status":"permitted","score":82,"pathway":"Permitted","zones":"C-1, C-2","special_use":false},"requirements":{"stacking_cars":5,"lot_size_sqft":null,"front_setback_ft":null},"stacking_issue":false,"moratorium":false,"zoning_map_url":"","confidence":"AI Estimate","verified":false,"override_reason":"","notes":"","population":17000},"Grafton, WI":{"name":"Grafton","state":"WI","composite":83,"factors":{"zoning":18,"process":16,"site":16,"competition":17,"political":16},"carwash":{"status":"permitted","score":83,"pathway":"Permitted","zones":"B-2","special_use":false},"drivethru":{"status":"permitted","score":83,"pathway":"Permitted","zones":"B-2","special_use":false,"stacking_cars":5},"collision":{"status":"permitted","score":81,"pathway":"Permitted","zones":"B-2, M-1","special_use":false},"autosales":{"status":"permitted","score":83,"pathway":"Permitted","zones":"B-2","special_use":false},"requirements":{"stacking_cars":5,"lot_size_sqft":null,"front_setback_ft":null},"stacking_issue":false,"moratorium":false,"zoning_map_url":"","confidence":"AI Estimate","verified":false,"override_reason":"","notes":"","population":11600},"Port Washington, WI":{"name":"Port Washington","state":"WI","composite":83,"factors":{"zoning":18,"process":16,"site":16,"competition":17,"political":16},"carwash":{"status":"permitted","score":83,"pathway":"Permitted","zones":"B-2","special_use":false},"drivethru":{"status":"permitted","score":83,"pathway":"Permitted","zones":"B-2","special_use":false,"stacking_cars":5},"collision":{"status":"permitted","score":81,"pathway":"Permitted","zones":"B-2, M-1","special_use":false},"autosales":{"status":"permitted","score":83,"pathway":"Permitted","zones":"B-2","special_use":false},"requirements":{"stacking_cars":5,"lot_size_sqft":null,"front_setback_ft":null},"stacking_issue":false,"moratorium":false,"zoning_map_url":"","confidence":"AI Estimate","verified":false,"override_reason":"","notes":"","population":11600},"Fitchburg, WI":{"name":"Fitchburg","state":"WI","composite":78,"factors":{"zoning":18,"process":15,"site":15,"competition":15,"political":15},"carwash":{"status":"likely_permitted","score":78,"pathway":"Permitted","zones":"CG, CH","special_use":false},"drivethru":{"status":"likely_permitted","score":78,"pathway":"Permitted","zones":"CG, CH","special_use":false,"stacking_cars":5},"collision":{"status":"likely_permitted","score":76,"pathway":"Permitted","zones":"CH, LI","special_use":false},"autosales":{"status":"likely_permitted","score":78,"pathway":"Permitted","zones":"CG, CH","special_use":false},"requirements":{"stacking_cars":5,"lot_size_sqft":null,"front_setback_ft":null},"stacking_issue":false,"moratorium":false,"zoning_map_url":"","confidence":"AI Estimate","verified":false,"override_reason":"","notes":"","population":28000},"Middleton, WI":{"name":"Middleton","state":"WI","composite":77,"factors":{"zoning":18,"process":15,"site":15,"competition":15,"political":15},"carwash":{"status":"likely_permitted","score":78,"pathway":"Permitted","zones":"C-2","special_use":false},"drivethru":{"status":"likely_permitted","score":78,"pathway":"Permitted","zones":"C-2","special_use":false,"stacking_cars":5},"collision":{"status":"likely_permitted","score":74,"pathway":"Permitted","zones":"C-2, M-1","special_use":false},"autosales":{"status":"likely_permitted","score":76,"pathway":"Permitted","zones":"C-2","special_use":false},"requirements":{"stacking_cars":5,"lot_size_sqft":null,"front_setback_ft":null},"stacking_issue":false,"moratorium":false,"zoning_map_url":"","confidence":"AI Estimate","verified":false,"override_reason":"","notes":"Near Madison \u2014 some design review friction.","population":19000},"Glendale, WI":{"name":"Glendale","state":"WI","composite":77,"factors":{"zoning":18,"process":15,"site":15,"competition":15,"political":15},"carwash":{"status":"likely_permitted","score":78,"pathway":"Permitted","zones":"B-3","special_use":false},"drivethru":{"status":"likely_permitted","score":78,"pathway":"Permitted","zones":"B-3","special_use":false,"stacking_cars":5},"collision":{"status":"likely_permitted","score":74,"pathway":"Permitted","zones":"B-3, M-1","special_use":false},"autosales":{"status":"likely_permitted","score":76,"pathway":"Permitted","zones":"B-3","special_use":false},"requirements":{"stacking_cars":5,"lot_size_sqft":null,"front_setback_ft":null},"stacking_issue":false,"moratorium":false,"zoning_map_url":"","confidence":"AI Estimate","verified":false,"override_reason":"","notes":"","population":13000},"Madison, WI":{"name":"Madison","state":"WI","composite":49,"factors":{"zoning":16,"process":8,"site":10,"competition":8,"political":9},"carwash":{"status":"conditional","score":51,"pathway":"Permitted","zones":"CC, CC-T","special_use":false},"drivethru":{"status":"conditional","score":53,"pathway":"Permitted","zones":"CC, NMX, TSS","special_use":false,"stacking_cars":8},"collision":{"status":"restrictive","score":45,"pathway":"Conditional Use","zones":"IL, IG","special_use":true},"autosales":{"status":"restrictive","score":45,"pathway":"Conditional Use","zones":"CC-T, SE","special_use":true},"requirements":{"stacking_cars":8,"lot_size_sqft":null,"front_setback_ft":null},"stacking_issue":false,"moratorium":false,"zoning_map_url":"https://cityofmadison.maps.arcgis.com","confidence":"AI Estimate","verified":false,"override_reason":"","notes":"Large city. Design review. Auto uses restricted in core.","population":269000},"Waukesha, WI":{"name":"Waukesha","state":"WI","composite":64,"factors":{"zoning":16,"process":12,"site":13,"competition":11,"political":12},"carwash":{"status":"conditional","score":64,"pathway":"Permitted","zones":"B-3, B-4","special_use":false},"drivethru":{"status":"likely_permitted","score":66,"pathway":"Permitted","zones":"B-3, B-4, B-5","special_use":false,"stacking_cars":6},"collision":{"status":"conditional","score":62,"pathway":"Permitted","zones":"B-4, M-1","special_use":false},"autosales":{"status":"conditional","score":64,"pathway":"Permitted","zones":"B-3, B-4, B-5","special_use":false},"requirements":{"stacking_cars":6,"lot_size_sqft":null,"front_setback_ft":null},"stacking_issue":false,"moratorium":false,"zoning_map_url":"https://www.ci.waukesha.wi.us/gis","confidence":"AI Estimate","verified":false,"override_reason":"","notes":"","population":72000},"Verona, WI":{"name":"Verona","state":"WI","composite":77,"factors":{"zoning":16,"process":15,"site":15,"competition":16,"political":15},"carwash":{"status":"likely_permitted","score":77,"pathway":"Permitted","zones":"C-1, C-2","special_use":false},"drivethru":{"status":"likely_permitted","score":79,"pathway":"Permitted","zones":"C-1, C-2","special_use":false,"stacking_cars":5},"collision":{"status":"likely_permitted","score":75,"pathway":"Permitted","zones":"C-2, M-1","special_use":false},"autosales":{"status":"likely_permitted","score":77,"pathway":"Permitted","zones":"C-1, C-2","special_use":false},"requirements":{"stacking_cars":5,"lot_size_sqft":null,"front_setback_ft":null},"stacking_issue":false,"moratorium":false,"zoning_map_url":"","confidence":"AI Estimate","verified":false,"override_reason":"","notes":"","population":13800},"Chicago, IL":{"name":"Chicago","state":"IL","composite":32,"factors":{"zoning":12,"process":3,"site":8,"competition":5,"political":6},"carwash":{"status":"restrictive","score":34,"pathway":"Conditional Use","zones":"B3-2, C1-2, C1-3","special_use":false},"drivethru":{"status":"restrictive","score":34,"pathway":"Conditional Use","zones":"B3-2, C1-2, C1-3","special_use":false,"stacking_cars":8},"collision":{"status":"restrictive","score":30,"pathway":"Special Use","zones":"C2-3, M1-2","special_use":true},"autosales":{"status":"restrictive","score":30,"pathway":"Special Use","zones":"C2-2, C2-3, M1-2","special_use":true},"requirements":{"stacking_cars":8,"lot_size_sqft":null,"front_setback_ft":null},"stacking_issue":false,"moratorium":false,"zoning_map_url":"https://gisapps.chicago.gov/ZoningMapWeb/","confidence":"AI Estimate","verified":false,"override_reason":"","notes":"Aldermanic approval is key. Massive process friction.","population":2700000},"Milwaukee, WI":{"name":"Milwaukee","state":"WI","composite":43,"factors":{"zoning":12,"process":7,"site":9,"competition":6,"political":8},"carwash":{"status":"restrictive","score":42,"pathway":"Conditional Use","zones":"LB2, CS","special_use":true},"drivethru":{"status":"restrictive","score":48,"pathway":"Permitted","zones":"LB2, CS, IL","special_use":false,"stacking_cars":8},"collision":{"status":"restrictive","score":40,"pathway":"Conditional Use","zones":"CS, IL, IG","special_use":true},"autosales":{"status":"restrictive","score":40,"pathway":"Conditional Use","zones":"CS, IL","special_use":true},"requirements":{"stacking_cars":8,"lot_size_sqft":null,"front_setback_ft":null},"stacking_issue":false,"moratorium":false,"zoning_map_url":"https://city.milwaukee.gov/maps","confidence":"AI Estimate","verified":false,"override_reason":"","notes":"Large metro. Auto uses face extra friction.","population":577000},"Wheaton, IL":{"name":"Wheaton","state":"IL","composite":58,"factors":{"zoning":12,"process":10,"site":13,"competition":11,"political":11},"carwash":{"status":"conditional","score":57,"pathway":"Conditional Use","zones":"C-3, C-4","special_use":true},"drivethru":{"status":"conditional","score":61,"pathway":"Permitted","zones":"C-3, C-4","special_use":false,"stacking_cars":8},"collision":{"status":"conditional","score":55,"pathway":"Conditional Use","zones":"C-4, M-1","special_use":true},"autosales":{"status":"conditional","score":57,"pathway":"Conditional Use","zones":"C-3, C-4","special_use":true},"requirements":{"stacking_cars":8,"lot_size_sqft":null,"front_setback_ft":null},"stacking_issue":false,"moratorium":false,"zoning_map_url":"","confidence":"AI Estimate","verified":false,"override_reason":"","notes":"","population":53000},"Skokie, IL":{"name":"Skokie","state":"IL","composite":53,"factors":{"zoning":12,"process":9,"site":12,"competition":10,"political":10},"carwash":{"status":"conditional","score":53,"pathway":"Conditional Use","zones":"B2, B3","special_use":true},"drivethru":{"status":"conditional","score":57,"pathway":"Permitted","zones":"B2, B3","special_use":false,"stacking_cars":8},"collision":{"status":"restrictive","score":49,"pathway":"Special Use","zones":"B3, M-1","special_use":true},"autosales":{"status":"conditional","score":51,"pathway":"Conditional Use","zones":"B2, B3","special_use":true},"requirements":{"stacking_cars":8,"lot_size_sqft":null,"front_setback_ft":null},"stacking_issue":false,"moratorium":false,"zoning_map_url":"https://www.skokie.org/maps","confidence":"AI Estimate","verified":false,"override_reason":"","notes":"Collision repair special use in commercial.","population":65000},"Arlington Heights, IL":{"name":"Arlington Heights","state":"IL","composite":51,"factors":{"zoning":12,"process":9,"site":12,"competition":10,"political":10},"carwash":{"status":"conditional","score":53,"pathway":"Conditional Use","zones":"B-3, B-4","special_use":true},"drivethru":{"status":"conditional","score":53,"pathway":"Conditional Use","zones":"B-3, B-4","special_use":true,"stacking_cars":8},"collision":{"status":"restrictive","score":49,"pathway":"Special Use","zones":"B-4, M-1","special_use":true},"autosales":{"status":"restrictive","score":49,"pathway":"Special Use","zones":"B-3, B-4","special_use":true},"requirements":{"stacking_cars":8,"lot_size_sqft":null,"front_setback_ft":null},"stacking_issue":false,"moratorium":false,"zoning_map_url":"https://www.vah.com/maps","confidence":"AI Estimate","verified":false,"override_reason":"","notes":"All auto uses face scrutiny.","population":76000},"Downers Grove, IL":{"name":"Downers Grove","state":"IL","composite":60,"factors":{"zoning":12,"process":11,"site":14,"competition":12,"political":12},"carwash":{"status":"conditional","score":61,"pathway":"Conditional Use","zones":"B-2, B-3","special_use":true},"drivethru":{"status":"conditional","score":61,"pathway":"Conditional Use","zones":"B-2, B-3","special_use":true,"stacking_cars":8},"collision":{"status":"conditional","score":59,"pathway":"Conditional Use","zones":"B-3, M-1","special_use":true},"autosales":{"status":"conditional","score":59,"pathway":"Conditional Use","zones":"B-2, B-3","special_use":true},"requirements":{"stacking_cars":8,"lot_size_sqft":null,"front_setback_ft":null},"stacking_issue":false,"moratorium":false,"zoning_map_url":"https://www.downers.us/maps","confidence":"AI Estimate","verified":false,"override_reason":"","notes":"","population":49000},"New Berlin, WI":{"name":"New Berlin","state":"WI","composite":69,"factors":{"zoning":12,"process":14,"site":14,"competition":13,"political":14},"carwash":{"status":"likely_permitted","score":67,"pathway":"Conditional Use","zones":"B-3","special_use":true},"drivethru":{"status":"likely_permitted","score":71,"pathway":"Permitted","zones":"B-2, B-3","special_use":false,"stacking_cars":6},"collision":{"status":"likely_permitted","score":69,"pathway":"Permitted","zones":"B-3, M-1","special_use":false},"autosales":{"status":"likely_permitted","score":69,"pathway":"Permitted","zones":"B-3","special_use":false},"requirements":{"stacking_cars":6,"lot_size_sqft":null,"front_setback_ft":null},"stacking_issue":false,"moratorium":false,"zoning_map_url":"","confidence":"AI Estimate","verified":false,"override_reason":"","notes":"","population":39000},"Palatine, IL":{"name":"Palatine","state":"IL","composite":56,"factors":{"zoning":12,"process":9,"site":13,"competition":11,"political":11},"carwash":{"status":"conditional","score":56,"pathway":"Conditional Use","zones":"B-3, B-4","special_use":true},"drivethru":{"status":"conditional","score":60,"pathway":"Permitted","zones":"B-3, B-4","special_use":false,"stacking_cars":8},"collision":{"status":"conditional","score":52,"pathway":"Special Use","zones":"B-4, M-1","special_use":true},"autosales":{"status":"conditional","score":54,"pathway":"Conditional Use","zones":"B-3, B-4","special_use":true},"requirements":{"stacking_cars":8,"lot_size_sqft":null,"front_setback_ft":null},"stacking_issue":false,"moratorium":false,"zoning_map_url":"","confidence":"AI Estimate","verified":false,"override_reason":"","notes":"","population":68000},"Rolling Meadows, IL":{"name":"Rolling Meadows","state":"IL","composite":70,"factors":{"zoning":12,"process":13,"site":15,"competition":14,"political":14},"carwash":{"status":"likely_permitted","score":68,"pathway":"Conditional Use","zones":"C-3","special_use":true},"drivethru":{"status":"likely_permitted","score":72,"pathway":"Permitted","zones":"C-3, C-4","special_use":false,"stacking_cars":6},"collision":{"status":"likely_permitted","score":68,"pathway":"Conditional Use","zones":"C-4, M-1","special_use":true},"autosales":{"status":"likely_permitted","score":70,"pathway":"Permitted","zones":"C-3, C-4","special_use":false},"requirements":{"stacking_cars":6,"lot_size_sqft":null,"front_setback_ft":null},"stacking_issue":false,"moratorium":false,"zoning_map_url":"","confidence":"AI Estimate","verified":false,"override_reason":"","notes":"","population":24000},"Mount Prospect, IL":{"name":"Mount Prospect","state":"IL","composite":57,"factors":{"zoning":12,"process":10,"site":13,"competition":11,"political":11},"carwash":{"status":"conditional","score":57,"pathway":"Conditional Use","zones":"B-3, B-4","special_use":true},"drivethru":{"status":"conditional","score":61,"pathway":"Permitted","zones":"B-3, B-4","special_use":false,"stacking_cars":8},"collision":{"status":"conditional","score":53,"pathway":"Special Use","zones":"B-4, M-1","special_use":true},"autosales":{"status":"conditional","score":55,"pathway":"Conditional Use","zones":"B-3, B-4","special_use":true},"requirements":{"stacking_cars":8,"lot_size_sqft":null,"front_setback_ft":null},"stacking_issue":false,"moratorium":false,"zoning_map_url":"","confidence":"AI Estimate","verified":false,"override_reason":"","notes":"","population":54000},"Hoffman Estates, IL":{"name":"Hoffman Estates","state":"IL","composite":58,"factors":{"zoning":12,"process":10,"site":13,"competition":11,"political":11},"carwash":{"status":"conditional","score":57,"pathway":"Conditional Use","zones":"B-3","special_use":true},"drivethru":{"status":"conditional","score":61,"pathway":"Permitted","zones":"B-2, B-3","special_use":false,"stacking_cars":6},"collision":{"status":"conditional","score":55,"pathway":"Conditional Use","zones":"B-3, M-1","special_use":true},"autosales":{"status":"conditional","score":57,"pathway":"Conditional Use","zones":"B-3","special_use":true},"requirements":{"stacking_cars":6,"lot_size_sqft":null,"front_setback_ft":null},"stacking_issue":false,"moratorium":false,"zoning_map_url":"","confidence":"AI Estimate","verified":false,"override_reason":"","notes":"","population":52000},"Northbrook, IL":{"name":"Northbrook","state":"IL","composite":55,"factors":{"zoning":12,"process":10,"site":13,"competition":12,"political":8},"carwash":{"status":"conditional","score":55,"pathway":"Conditional Use","zones":"C-3","special_use":true},"drivethru":{"status":"conditional","score":59,"pathway":"Permitted","zones":"C-2, C-3","special_use":false,"stacking_cars":8},"collision":{"status":"conditional","score":51,"pathway":"Special Use","zones":"C-4, M-1","special_use":true},"autosales":{"status":"conditional","score":51,"pathway":"Special Use","zones":"C-3, C-4","special_use":true},"requirements":{"stacking_cars":8,"lot_size_sqft":null,"front_setback_ft":null},"stacking_issue":false,"moratorium":false,"zoning_map_url":"https://www.northbrook.il.us/maps","confidence":"AI Estimate","verified":false,"override_reason":"","notes":"Affluent. Auto-intensive uses face resistance.","population":33000},"Glenview, IL":{"name":"Glenview","state":"IL","composite":56,"factors":{"zoning":12,"process":10,"site":13,"competition":12,"political":9},"carwash":{"status":"conditional","score":56,"pathway":"Conditional Use","zones":"B-3","special_use":true},"drivethru":{"status":"conditional","score":60,"pathway":"Permitted","zones":"B-2, B-3","special_use":false,"stacking_cars":8},"collision":{"status":"conditional","score":52,"pathway":"Special Use","zones":"B-3, M-1","special_use":true},"autosales":{"status":"conditional","score":52,"pathway":"Special Use","zones":"B-3","special_use":true},"requirements":{"stacking_cars":8,"lot_size_sqft":null,"front_setback_ft":null},"stacking_issue":false,"moratorium":false,"zoning_map_url":"","confidence":"AI Estimate","verified":false,"override_reason":"","notes":"","population":47000},"Elmhurst, IL":{"name":"Elmhurst","state":"IL","composite":61,"factors":{"zoning":12,"process":11,"site":14,"competition":12,"political":12},"carwash":{"status":"conditional","score":61,"pathway":"Conditional Use","zones":"C-3, C-4","special_use":true},"drivethru":{"status":"likely_permitted","score":65,"pathway":"Permitted","zones":"C-3, C-4","special_use":false,"stacking_cars":8},"collision":{"status":"conditional","score":57,"pathway":"Special Use","zones":"C-4, M-1","special_use":true},"autosales":{"status":"conditional","score":59,"pathway":"Conditional Use","zones":"C-3, C-4","special_use":true},"requirements":{"stacking_cars":8,"lot_size_sqft":null,"front_setback_ft":null},"stacking_issue":false,"moratorium":false,"zoning_map_url":"","confidence":"AI Estimate","verified":false,"override_reason":"","notes":"","population":46000},"Lombard, IL":{"name":"Lombard","state":"IL","composite":63,"factors":{"zoning":12,"process":11,"site":14,"competition":13,"political":12},"carwash":{"status":"conditional","score":62,"pathway":"Conditional Use","zones":"B-3","special_use":true},"drivethru":{"status":"likely_permitted","score":66,"pathway":"Permitted","zones":"B-2, B-3","special_use":false,"stacking_cars":8},"collision":{"status":"conditional","score":60,"pathway":"Conditional Use","zones":"B-3, M-1","special_use":true},"autosales":{"status":"conditional","score":62,"pathway":"Conditional Use","zones":"B-3","special_use":true},"requirements":{"stacking_cars":8,"lot_size_sqft":null,"front_setback_ft":null},"stacking_issue":false,"moratorium":false,"zoning_map_url":"","confidence":"AI Estimate","verified":false,"override_reason":"","notes":"","population":44000},"Orland Park, IL":{"name":"Orland Park","state":"IL","composite":58,"factors":{"zoning":12,"process":10,"site":13,"competition":11,"political":11},"carwash":{"status":"conditional","score":57,"pathway":"Conditional Use","zones":"B-3, B-4","special_use":true},"drivethru":{"status":"conditional","score":61,"pathway":"Permitted","zones":"B-3, B-4","special_use":false,"stacking_cars":8},"collision":{"status":"conditional","score":55,"pathway":"Conditional Use","zones":"B-4, M-1","special_use":true},"autosales":{"status":"conditional","score":57,"pathway":"Conditional Use","zones":"B-3, B-4","special_use":true},"requirements":{"stacking_cars":8,"lot_size_sqft":null,"front_setback_ft":null},"stacking_issue":false,"moratorium":false,"zoning_map_url":"https://www.orlandpark.org/maps","confidence":"AI Estimate","verified":false,"override_reason":"","notes":"","population":58000},"Brookfield, WI":{"name":"Brookfield","state":"WI","composite":61,"factors":{"zoning":12,"process":13,"site":14,"competition":12,"political":12},"carwash":{"status":"conditional","score":63,"pathway":"Conditional Use","zones":"B-3","special_use":true},"drivethru":{"status":"conditional","score":59,"pathway":"Special Use","zones":"B-3","special_use":true,"stacking_cars":10},"collision":{"status":"conditional","score":61,"pathway":"Conditional Use","zones":"B-3, M-1","special_use":true},"autosales":{"status":"conditional","score":63,"pathway":"Conditional Use","zones":"B-3","special_use":true},"requirements":{"stacking_cars":10,"lot_size_sqft":null,"front_setback_ft":null},"stacking_issue":true,"moratorium":false,"zoning_map_url":"https://www.ci.brookfield.wi.us/maps","confidence":"AI Estimate","verified":false,"override_reason":"","notes":"Stacking issues for DT. 10-car requirement.","population":38000},"Evanston, IL":{"name":"Evanston","state":"IL","composite":48,"factors":{"zoning":8,"process":8,"site":11,"competition":10,"political":9},"carwash":{"status":"restrictive","score":46,"pathway":"Special Use","zones":"C1a, C2","special_use":true},"drivethru":{"status":"conditional","score":54,"pathway":"Permitted","zones":"C1, C1a, C2","special_use":false,"stacking_cars":8},"collision":{"status":"restrictive","score":44,"pathway":"Special Use","zones":"C2, I1","special_use":true},"autosales":{"status":"restrictive","score":44,"pathway":"Special Use","zones":"C2","special_use":true},"requirements":{"stacking_cars":8,"lot_size_sqft":null,"front_setback_ft":null},"stacking_issue":false,"moratorium":false,"zoning_map_url":"https://www.cityofevanston.org/maps","confidence":"AI Estimate","verified":false,"override_reason":"","notes":"Dense urban. Anti-auto sentiment. High process friction.","population":74000},"Oak Park, IL":{"name":"Oak Park","state":"IL","composite":48,"factors":{"zoning":8,"process":8,"site":11,"competition":10,"political":9},"carwash":{"status":"restrictive","score":46,"pathway":"Special Use","zones":"B (Business)","special_use":true},"drivethru":{"status":"conditional","score":54,"pathway":"Permitted","zones":"B (Business)","special_use":false,"stacking_cars":8},"collision":{"status":"restrictive","score":44,"pathway":"Special Use","zones":"B, I (Industrial)","special_use":true},"autosales":{"status":"restrictive","score":44,"pathway":"Special Use","zones":"B (Business)","special_use":true},"requirements":{"stacking_cars":8,"lot_size_sqft":null,"front_setback_ft":null},"stacking_issue":false,"moratorium":false,"zoning_map_url":"","confidence":"AI Estimate","verified":false,"override_reason":"","notes":"Progressive suburb. Anti-auto sprawl sentiment.","population":52000},"Mequon, WI":{"name":"Mequon","state":"WI","composite":63,"factors":{"zoning":8,"process":14,"site":14,"competition":14,"political":10},"carwash":{"status":"conditional","score":60,"pathway":"Special Use","zones":"B-2","special_use":true},"drivethru":{"status":"likely_permitted","score":68,"pathway":"Permitted","zones":"B-2","special_use":false,"stacking_cars":6},"collision":{"status":"conditional","score":62,"pathway":"Conditional Use","zones":"B-2, M-1","special_use":true},"autosales":{"status":"conditional","score":62,"pathway":"Conditional Use","zones":"B-2","special_use":true},"requirements":{"stacking_cars":6,"lot_size_sqft":null,"front_setback_ft":null},"stacking_issue":false,"moratorium":false,"zoning_map_url":"","confidence":"AI Estimate","verified":false,"override_reason":"","notes":"Affluent suburb.","population":24000},"Shorewood, WI":{"name":"Shorewood","state":"WI","composite":52,"factors":{"zoning":8,"process":12,"site":12,"competition":12,"political":8},"carwash":{"status":"conditional","score":52,"pathway":"Special Use","zones":"B-4","special_use":true},"drivethru":{"status":"conditional","score":56,"pathway":"Conditional Use","zones":"B-4","special_use":true,"stacking_cars":6},"collision":{"status":"restrictive","score":48,"pathway":"Prohibited","zones":"None","special_use":false},"autosales":{"status":"restrictive","score":48,"pathway":"Prohibited","zones":"None","special_use":false},"requirements":{"stacking_cars":6,"lot_size_sqft":null,"front_setback_ft":null},"stacking_issue":false,"moratorium":false,"zoning_map_url":"","confidence":"AI Estimate","verified":false,"override_reason":"","notes":"Dense, walkable. Anti-auto. No auto-intensive uses allowed.","population":13000},"Park Ridge, IL":{"name":"Park Ridge","state":"IL","composite":54,"factors":{"zoning":8,"process":10,"site":13,"competition":12,"political":9},"carwash":{"status":"conditional","score":52,"pathway":"Special Use","zones":"C-3","special_use":true},"drivethru":{"status":"conditional","score":60,"pathway":"Permitted","zones":"C-2, C-3","special_use":false,"stacking_cars":8},"collision":{"status":"conditional","score":50,"pathway":"Special Use","zones":"C-4, M-1","special_use":true},"autosales":{"status":"conditional","score":52,"pathway":"Special Use","zones":"C-3","special_use":true},"requirements":{"stacking_cars":8,"lot_size_sqft":null,"front_setback_ft":null},"stacking_issue":false,"moratorium":false,"zoning_map_url":"","confidence":"AI Estimate","verified":false,"override_reason":"","notes":"","population":37000},"Wilmette, IL":{"name":"Wilmette","state":"IL","composite":47,"factors":{"zoning":8,"process":9,"site":12,"competition":12,"political":6},"carwash":{"status":"restrictive","score":47,"pathway":"Special Use","zones":"GC-1","special_use":true},"drivethru":{"status":"conditional","score":51,"pathway":"Conditional Use","zones":"GC-1, NR","special_use":true,"stacking_cars":8},"collision":{"status":"restrictive","score":43,"pathway":"Special Use","zones":"GC-1","special_use":true},"autosales":{"status":"restrictive","score":45,"pathway":"Special Use","zones":"GC-1","special_use":true},"requirements":{"stacking_cars":8,"lot_size_sqft":null,"front_setback_ft":null},"stacking_issue":false,"moratorium":false,"zoning_map_url":"","confidence":"AI Estimate","verified":false,"override_reason":"","notes":"North Shore. Very restrictive for auto uses.","population":28000},"Highland Park, IL":{"name":"Highland Park","state":"IL","composite":47,"factors":{"zoning":8,"process":9,"site":12,"competition":12,"political":6},"carwash":{"status":"restrictive","score":47,"pathway":"Special Use","zones":"B-5","special_use":true},"drivethru":{"status":"conditional","score":51,"pathway":"Conditional Use","zones":"B-3, B-5","special_use":true,"stacking_cars":8},"collision":{"status":"restrictive","score":43,"pathway":"Special Use","zones":"B-5, M-1","special_use":true},"autosales":{"status":"restrictive","score":45,"pathway":"Special Use","zones":"B-5","special_use":true},"requirements":{"stacking_cars":8,"lot_size_sqft":null,"front_setback_ft":null},"stacking_issue":false,"moratorium":false,"zoning_map_url":"","confidence":"AI Estimate","verified":false,"override_reason":"","notes":"","population":30000},"Deerfield, IL":{"name":"Deerfield","state":"IL","composite":57,"factors":{"zoning":8,"process":11,"site":14,"competition":13,"political":9},"carwash":{"status":"conditional","score":55,"pathway":"Special Use","zones":"C-2, C-3","special_use":true},"drivethru":{"status":"conditional","score":63,"pathway":"Permitted","zones":"C-2, C-3","special_use":false,"stacking_cars":8},"collision":{"status":"conditional","score":53,"pathway":"Special Use","zones":"C-3, M-1","special_use":true},"autosales":{"status":"conditional","score":55,"pathway":"Special Use","zones":"C-3","special_use":true},"requirements":{"stacking_cars":8,"lot_size_sqft":null,"front_setback_ft":null},"stacking_issue":false,"moratorium":false,"zoning_map_url":"","confidence":"AI Estimate","verified":false,"override_reason":"","notes":"","population":19000},"Lake Forest, IL":{"name":"Lake Forest","state":"IL","composite":49,"factors":{"zoning":8,"process":9,"site":13,"competition":13,"political":6},"carwash":{"status":"restrictive","score":49,"pathway":"Special Use","zones":"GC-1","special_use":true},"drivethru":{"status":"conditional","score":53,"pathway":"Conditional Use","zones":"GC-1","special_use":true,"stacking_cars":8},"collision":{"status":"restrictive","score":45,"pathway":"Special Use","zones":"GC-1, LI","special_use":true},"autosales":{"status":"restrictive","score":45,"pathway":"Special Use","zones":"GC-1","special_use":true},"requirements":{"stacking_cars":8,"lot_size_sqft":null,"front_setback_ft":null},"stacking_issue":false,"moratorium":false,"zoning_map_url":"","confidence":"AI Estimate","verified":false,"override_reason":"","notes":"Very affluent. Strict design standards. Historic preservation.","population":19000},"Libertyville, IL":{"name":"Libertyville","state":"IL","composite":66,"factors":{"zoning":12,"process":12,"site":15,"competition":14,"political":13},"carwash":{"status":"likely_permitted","score":66,"pathway":"Conditional Use","zones":"B-3","special_use":true},"drivethru":{"status":"likely_permitted","score":70,"pathway":"Permitted","zones":"B-2, B-3","special_use":false,"stacking_cars":6},"collision":{"status":"conditional","score":64,"pathway":"Conditional Use","zones":"B-3, M-1","special_use":true},"autosales":{"status":"conditional","score":64,"pathway":"Conditional Use","zones":"B-3","special_use":true},"requirements":{"stacking_cars":6,"lot_size_sqft":null,"front_setback_ft":null},"stacking_issue":false,"moratorium":false,"zoning_map_url":"","confidence":"AI Estimate","verified":false,"override_reason":"","notes":"","population":20000},"Palos Hills, IL":{"name":"Palos Hills","state":"IL","composite":67,"factors":{"zoning":12,"process":12,"site":15,"competition":14,"political":13},"carwash":{"status":"likely_permitted","score":66,"pathway":"Conditional Use","zones":"C-2, C-3","special_use":true},"drivethru":{"status":"likely_permitted","score":70,"pathway":"Permitted","zones":"C-2, C-3","special_use":false,"stacking_cars":6},"collision":{"status":"conditional","score":64,"pathway":"Conditional Use","zones":"C-3, M-1","special_use":true},"autosales":{"status":"likely_permitted","score":66,"pathway":"Permitted","zones":"C-2, C-3","special_use":false},"requirements":{"stacking_cars":6,"lot_size_sqft":null,"front_setback_ft":null},"stacking_issue":false,"moratorium":false,"zoning_map_url":"","confidence":"AI Estimate","verified":false,"override_reason":"","notes":"","population":18000},"Darien, IL":{"name":"Darien","state":"IL","composite":67,"factors":{"zoning":12,"process":12,"site":15,"competition":14,"political":13},"carwash":{"status":"likely_permitted","score":66,"pathway":"Conditional Use","zones":"B-2, B-3","special_use":true},"drivethru":{"status":"likely_permitted","score":70,"pathway":"Permitted","zones":"B-2, B-3","special_use":false,"stacking_cars":6},"collision":{"status":"conditional","score":64,"pathway":"Conditional Use","zones":"B-3, M-1","special_use":true},"autosales":{"status":"likely_permitted","score":66,"pathway":"Permitted","zones":"B-2, B-3","special_use":false},"requirements":{"stacking_cars":6,"lot_size_sqft":null,"front_setback_ft":null},"stacking_issue":false,"moratorium":false,"zoning_map_url":"","confidence":"AI Estimate","verified":false,"override_reason":"","notes":"","population":22000},"Hinsdale, IL":{"name":"Hinsdale","state":"IL","composite":47,"factors":{"zoning":8,"process":9,"site":13,"competition":13,"political":5},"carwash":{"status":"restrictive","score":48,"pathway":"Special Use","zones":"B-1, B-2","special_use":true},"drivethru":{"status":"conditional","score":52,"pathway":"Conditional Use","zones":"B-1, B-2","special_use":true,"stacking_cars":10},"collision":{"status":"restrictive","score":40,"pathway":"Prohibited","zones":"None","special_use":false},"autosales":{"status":"restrictive","score":46,"pathway":"Special Use","zones":"B-2","special_use":true},"requirements":{"stacking_cars":10,"lot_size_sqft":null,"front_setback_ft":null},"stacking_issue":true,"moratorium":false,"zoning_map_url":"","confidence":"AI Estimate","verified":false,"override_reason":"","notes":"Very affluent. No collision repair. 10-car stacking. Design review board.","population":17000},"Westmont, IL":{"name":"Westmont","state":"IL","composite":67,"factors":{"zoning":12,"process":12,"site":15,"competition":14,"political":13},"carwash":{"status":"likely_permitted","score":66,"pathway":"Conditional Use","zones":"B-2, B-3","special_use":true},"drivethru":{"status":"likely_permitted","score":70,"pathway":"Permitted","zones":"B-2, B-3","special_use":false,"stacking_cars":6},"collision":{"status":"conditional","score":64,"pathway":"Conditional Use","zones":"B-3, M-1","special_use":true},"autosales":{"status":"likely_permitted","score":66,"pathway":"Permitted","zones":"B-2, B-3","special_use":false},"requirements":{"stacking_cars":6,"lot_size_sqft":null,"front_setback_ft":null},"stacking_issue":false,"moratorium":false,"zoning_map_url":"","confidence":"AI Estimate","verified":false,"override_reason":"","notes":"","population":24000},"Cedarburg, WI":{"name":"Cedarburg","state":"WI","composite":63,"factors":{"zoning":8,"process":13,"site":14,"competition":14,"political":12},"carwash":{"status":"conditional","score":61,"pathway":"Special Use","zones":"B-2","special_use":true},"drivethru":{"status":"likely_permitted","score":65,"pathway":"Conditional Use","zones":"B-2","special_use":true,"stacking_cars":6},"collision":{"status":"conditional","score":63,"pathway":"Conditional Use","zones":"B-2, M-1","special_use":true},"autosales":{"status":"conditional","score":63,"pathway":"Conditional Use","zones":"B-2","special_use":true},"requirements":{"stacking_cars":6,"lot_size_sqft":null,"front_setback_ft":null},"stacking_issue":false,"moratorium":false,"zoning_map_url":"","confidence":"AI Estimate","verified":false,"override_reason":"","notes":"Historic downtown. Aesthetic concerns.","population":12000},"Barrington, IL":{"name":"Barrington","state":"IL","composite":54,"factors":{"zoning":8,"process":11,"site":14,"competition":14,"political":7},"carwash":{"status":"conditional","score":54,"pathway":"Special Use","zones":"B-3","special_use":true},"drivethru":{"status":"conditional","score":56,"pathway":"Conditional Use","zones":"B-3","special_use":true,"stacking_cars":8},"collision":{"status":"conditional","score":52,"pathway":"Special Use","zones":"B-3, M-1","special_use":true},"autosales":{"status":"conditional","score":54,"pathway":"Special Use","zones":"B-3","special_use":true},"requirements":{"stacking_cars":8,"lot_size_sqft":null,"front_setback_ft":null},"stacking_issue":false,"moratorium":false,"zoning_map_url":"","confidence":"AI Estimate","verified":false,"override_reason":"","notes":"Affluent. Community character concerns.","population":10000},"Glencoe, IL":{"name":"Glencoe","state":"IL","composite":48,"factors":{"zoning":8,"process":10,"site":13,"competition":14,"political":6},"carwash":{"status":"conditional","score":51,"pathway":"Special Use","zones":"C-Comm","special_use":true},"drivethru":{"status":"conditional","score":51,"pathway":"Special Use","zones":"C-Comm","special_use":true,"stacking_cars":8},"collision":{"status":"restrictive","score":43,"pathway":"Prohibited","zones":"None","special_use":false},"autosales":{"status":"restrictive","score":43,"pathway":"Prohibited","zones":"None","special_use":false},"requirements":{"stacking_cars":8,"lot_size_sqft":null,"front_setback_ft":null},"stacking_issue":false,"moratorium":false,"zoning_map_url":"","confidence":"AI Estimate","verified":false,"override_reason":"","notes":"Very affluent North Shore. Auto uses extremely restricted.","population":9000},"Winnetka, IL":{"name":"Winnetka","state":"IL","composite":44,"factors":{"zoning":8,"process":9,"site":12,"competition":13,"political":5},"carwash":{"status":"restrictive","score":47,"pathway":"Special Use","zones":"C-Comm","special_use":true},"drivethru":{"status":"restrictive","score":47,"pathway":"Special Use","zones":"C-Comm","special_use":true,"stacking_cars":8},"collision":{"status":"restrictive","score":39,"pathway":"Prohibited","zones":"None","special_use":false},"autosales":{"status":"restrictive","score":39,"pathway":"Prohibited","zones":"None","special_use":false},"requirements":{"stacking_cars":8,"lot_size_sqft":null,"front_setback_ft":null},"stacking_issue":true,"moratorium":false,"zoning_map_url":"","confidence":"AI Estimate","verified":false,"override_reason":"","notes":"Extremely affluent. Auto uses extremely restricted.","population":12000},"Clarendon Hills, IL":{"name":"Clarendon Hills","state":"IL","composite":62,"factors":{"zoning":8,"process":12,"site":15,"competition":15,"political":11},"carwash":{"status":"conditional","score":61,"pathway":"Special Use","zones":"B-1","special_use":true},"drivethru":{"status":"likely_permitted","score":65,"pathway":"Conditional Use","zones":"B-1","special_use":true,"stacking_cars":8},"collision":{"status":"conditional","score":59,"pathway":"Special Use","zones":"B-1, M-1","special_use":true},"autosales":{"status":"conditional","score":61,"pathway":"Special Use","zones":"B-1","special_use":true},"requirements":{"stacking_cars":8,"lot_size_sqft":null,"front_setback_ft":null},"stacking_issue":false,"moratorium":false,"zoning_map_url":"","confidence":"AI Estimate","verified":false,"override_reason":"","notes":"","population":9000},"Naperville, IL":{"name":"Naperville","state":"IL","composite":35,"factors":{"zoning":10,"process":6,"site":10,"competition":8,"political":4},"carwash":{"status":"restrictive","score":38,"pathway":"Conditional Use","zones":"B-3 only","special_use":true},"drivethru":{"status":"restrictive","score":34,"pathway":"Special Use","zones":"B-3 only (B-2 = Special Use)","special_use":true,"stacking_cars":10},"collision":{"status":"restrictive","score":36,"pathway":"Special Use","zones":"B-3, M-1","special_use":true},"autosales":{"status":"restrictive","score":38,"pathway":"Conditional Use","zones":"B-3, B-4","special_use":true},"requirements":{"stacking_cars":10,"lot_size_sqft":null,"front_setback_ft":null},"stacking_issue":true,"moratorium":false,"zoning_map_url":"https://www.naperville.il.us/maps","confidence":"High","verified":true,"override_reason":"Ground truth: Dutch Bros DENIED on Napier Blvd. 7 Brew at 1203 Iroquois only w/ extensive conditions.","notes":"Ground truth: Dutch Bros DENIED on Napier Blvd.","population":149000},"Schaumburg, IL":{"name":"Schaumburg","state":"IL","composite":49,"factors":{"zoning":12,"process":8,"site":12,"competition":10,"political":9},"carwash":{"status":"conditional","score":51,"pathway":"Conditional Use","zones":"B-2, B-3","special_use":true},"drivethru":{"status":"restrictive","score":47,"pathway":"Special Use","zones":"B-3 only","special_use":true,"stacking_cars":10},"collision":{"status":"restrictive","score":47,"pathway":"Special Use","zones":"B-3, M-1","special_use":true},"autosales":{"status":"restrictive","score":49,"pathway":"Conditional Use","zones":"B-2, B-3","special_use":true},"requirements":{"stacking_cars":10,"lot_size_sqft":null,"front_setback_ft":null},"stacking_issue":true,"moratorium":false,"zoning_map_url":"https://www.schaumburg.com/maps","confidence":"AI Estimate","verified":false,"override_reason":"","notes":"10-car stacking. Auto uses face extra scrutiny.","population":74000},"Kenilworth, IL":{"name":"Kenilworth","state":"IL","composite":41,"factors":{"zoning":0,"process":9,"site":12,"competition":16,"political":4},"carwash":{"status":"restrictive","score":41,"pathway":"Prohibited","zones":"None","special_use":false},"drivethru":{"status":"restrictive","score":41,"pathway":"Prohibited","zones":"None","special_use":false,"stacking_cars":null},"collision":{"status":"restrictive","score":41,"pathway":"Prohibited","zones":"None","special_use":false},"autosales":{"status":"restrictive","score":41,"pathway":"Prohibited","zones":"None","special_use":false},"requirements":{"stacking_cars":null,"lot_size_sqft":null,"front_setback_ft":null},"stacking_issue":false,"moratorium":false,"zoning_map_url":"","confidence":"AI Estimate","verified":false,"override_reason":"","notes":"Exclusively residential village. No commercial zones.","population":2500}}